coderepoindex/__init__.py
coderepoindex/cli.py
coderepoindex/config/__init__.py
coderepoindex/config/config_manager.py
coderepoindex/config/defaults.py
coderepoindex/core/__init__.py
coderepoindex/core/indexer.py
coderepoindex/core/models.py
coderepoindex/core/project_manager.py
coderepoindex/core/searcher.py
coderepoindex/core/storage_adapter.py
coderepoindex/embeddings/__init__.py
coderepoindex/embeddings/base.py
coderepoindex/embeddings/document_store.py
coderepoindex/embeddings/indexer.py
coderepoindex/embeddings/node.py
coderepoindex/embeddings/retriever.py
coderepoindex/embeddings/utils.py
coderepoindex/embeddings/vector_store.py
coderepoindex/models/__init__.py
coderepoindex/models/api_providers.py
coderepoindex/models/base.py
coderepoindex/models/factory.py
coderepoindex/models/utils.py
coderepoindex/parsers/__init__.py
coderepoindex/parsers/check_dependencies.py
coderepoindex/parsers/code_parser.py
coderepoindex/parsers/config.py
coderepoindex/parsers/directory_parser.py
coderepoindex/parsers/logger_config.py
coderepoindex/parsers/version_manager.py
coderepoindex/parsers/tests/test_all_parsers.py
coderepoindex/parsers/tests/test_c_parser.py
coderepoindex/parsers/tests/test_cpp_parser.py
coderepoindex/parsers/tests/test_go_parser.py
coderepoindex/parsers/tests/test_java_parser.py
coderepoindex/parsers/tests/test_javascript_parser.py
coderepoindex/parsers/tests/test_kotlin_parser.py
coderepoindex/parsers/tests/test_lua_parser.py
coderepoindex/parsers/tests/test_python_parser.py
coderepoindex/parsers/tests/test_typescript_parser.py
coderepoindex/repository/__init__.py
coderepoindex/repository/repo_fetcher.py
coderepoindex-0.1.0.dist-info/licenses/LICENSE
docs/conf.py
examples/basic_usage.py
examples/directory_parser_demo.py
examples/embedding_demo.py
examples/logger_demo.py
examples/metadata_search_demo.py
examples/models_demo.py
examples/parser_demo.py
examples/repository_demo.py
examples/sync_test_demo.py
examples/vector_search_demo.py
coderepoindex-0.1.0.dist-info/METADATA
coderepoindex-0.1.0.dist-info/WHEEL
coderepoindex-0.1.0.dist-info/entry_points.txt
coderepoindex-0.1.0.dist-info/top_level.txt
coderepoindex-0.1.0.dist-info/RECORD
