Metadata-Version: 2.4
Name: coderepoindex
Version: 0.1.0
Summary: 通过语义理解提高代码仓库的可发现性和可搜索性
Author-email: CodeRepoIndex Team <zhongxingyuemail@gmail.com>
License: MIT License
Project-URL: Homepage, https://github.com/XingYu-Zhong/CodeRepoIndex
Project-URL: Bug Reports, https://github.com/XingYu-Zhong/CodeRepoIndex/issues
Project-URL: Source, https://github.com/XingYu-Zhong/CodeRepoIndex
Project-URL: Documentation, https://coderepoindex.readthedocs.io/
Keywords: code search,vector search,semantic search,code indexing
Classifier: Development Status :: 3 - Alpha
Classifier: Intended Audience :: Developers
Classifier: Topic :: Software Development :: Libraries :: Python Modules
Classifier: Topic :: Software Development :: Version Control :: Git
Classifier: Programming Language :: Python :: 3
Classifier: Programming Language :: Python :: 3.8
Classifier: Programming Language :: Python :: 3.9
Classifier: Programming Language :: Python :: 3.10
Classifier: Programming Language :: Python :: 3.11
Requires-Python: >=3.8
License-File: LICENSE
Requires-Dist: numpy>=1.21.0
Requires-Dist: pandas>=1.3.0
Requires-Dist: sentence-transformers>=2.2.0
Requires-Dist: transformers>=4.20.0
Requires-Dist: torch>=1.12.0
Requires-Dist: faiss-cpu>=1.7.0
Requires-Dist: scikit-learn>=1.1.0
Requires-Dist: tree-sitter>=0.20.0
Requires-Dist: pygments>=2.10.0
Requires-Dist: gitpython>=3.1.0
Requires-Dist: pathspec>=0.9.0
Requires-Dist: chardet>=5.0.0
Requires-Dist: joblib>=1.1.0
Requires-Dist: h5py>=3.7.0
Requires-Dist: chromadb>=0.4.0
Requires-Dist: fastapi>=0.95.0
Requires-Dist: uvicorn[standard]>=0.20.0
Requires-Dist: python-dotenv>=0.19.0
Requires-Dist: pyyaml>=6.0
Requires-Dist: loguru>=0.6.0
Provides-Extra: dev
Requires-Dist: pytest>=7.0.0; extra == "dev"
Requires-Dist: pytest-cov>=4.0.0; extra == "dev"
Requires-Dist: pytest-mock>=3.10.0; extra == "dev"
Requires-Dist: pytest-asyncio>=0.21.0; extra == "dev"
Requires-Dist: black>=22.0.0; extra == "dev"
Requires-Dist: isort>=5.12.0; extra == "dev"
Requires-Dist: flake8>=5.0.0; extra == "dev"
Requires-Dist: mypy>=0.950; extra == "dev"
Requires-Dist: pylint>=2.15.0; extra == "dev"
Requires-Dist: bandit>=1.7.0; extra == "dev"
Requires-Dist: safety>=2.3.0; extra == "dev"
Requires-Dist: pre-commit>=2.20.0; extra == "dev"
Provides-Extra: docs
Requires-Dist: sphinx<8.0.0,>=5.0.0; extra == "docs"
Requires-Dist: sphinx-rtd-theme>=1.2.0; extra == "docs"
Requires-Dist: myst-parser<4.0.0,>=0.18.0; extra == "docs"
Requires-Dist: sphinxcontrib-mermaid>=0.7.0; extra == "docs"
Dynamic: license-file
